Savetube/__init__.py
Savetube/__main__.py
Savetube/ffmpeg.py
Savetube/version.py
Savetube/youtubedltojson.py
Savetube/GUI/__init__.py
Savetube/GUI/__main__.py
Savetube/GUI/downloadvideo.py
Savetube/GUI/folder.png
Savetube/GUI/gif2canvas.py
Savetube/GUI/icon.png
Savetube/GUI/loading.gif
Savetube/GUI/loadinganim.py
Savetube/GUI/scrollableframe.py
Savetube-1.1.data/scripts/savetube.py
test/__init__.py
test/test_youtubedltojson.py
Savetube-1.1.dist-info/LICENSE
Savetube-1.1.dist-info/METADATA
Savetube-1.1.dist-info/WHEEL
Savetube-1.1.dist-info/entry_points.txt
Savetube-1.1.dist-info/top_level.txt
Savetube-1.1.dist-info/RECORD
