Metadata-Version: 2.1
Name: Savetube
Version: 1.1
Summary: Youtube-dl GUI Wrapper
Home-page: http://github.com/bawaviki/savetube
Author: bawaviki
Author-email: bawaviki99@gmail.com
License: MIT
Download-URL: https://github.com/bawaviki/savetube/archive/v_1.1.tar.gz
Keywords: savetube,youtube-dl-gui,SavTube,Savetube,youtube-dl GUI
Platform: UNKNOWN
Classifier: Development Status :: 3 - Alpha
Classifier: Topic :: Utilities
Classifier: License :: OSI Approved :: MIT License
Requires-Python: >=3
Requires-Dist: youtube-dl
Requires-Dist: pyfiglet
Requires-Dist: termcolor
